pybio/__init__.py
pybio/pybio.config.example
pybio/version
pybio/aimux/__init__.py
pybio/config/__init__.py
pybio/core/__init__.py
pybio/core/genomes.py
pybio/data/Bedgraph.py
pybio/data/Fasta.py
pybio/data/Fastq.py
pybio/data/__init__.py
pybio/maths/__init__.py
pybio/path/__init__.py
pybio/sequence/__init__.py
pybio/utils/__init__.py
pybio-0.8.3.dist-info/licenses/LICENSE
pybio-0.8.3.dist-info/METADATA
pybio-0.8.3.dist-info/WHEEL
pybio-0.8.3.dist-info/entry_points.txt
pybio-0.8.3.dist-info/top_level.txt
pybio-0.8.3.dist-info/RECORD
