Metadata-Version: 2.4
Name: pybio
Version: 0.8.3
Summary: pybio genomics
Home-page: https://github.com/grexor/pybio
Author: Gregor Rot
Author-email: gregor.rot@gmail.com
License: GNU General Public License v3.0
Keywords: pybio,bioinformatics
Classifier: Programming Language :: Python :: 3
Classifier: License :: OSI Approved :: GNU General Public License v3 (GPLv3)
License-File: LICENSE
Requires-Dist: pysam
Requires-Dist: numpy
Requires-Dist: psutil
Requires-Dist: bs4
Requires-Dist: requests
Dynamic: author
Dynamic: author-email
Dynamic: classifier
Dynamic: description
Dynamic: description-content-type
Dynamic: home-page
Dynamic: keywords
Dynamic: license
Dynamic: license-file
Dynamic: requires-dist
Dynamic: summary
